[
	{
		"alias": "harmony",
		"name": "Harmony",
		"logo": "https://cryptologos.cc/logos/harmony-one-logo.svg",
		"address": "",
		"chain": {
			"chainId": "0x63564c40",
			"chainName": "Harmony Mainnet",
			"nativeCurrency": {
				"name": "ONE",
				"symbol": "ONE",
				"decimals": 18
			},
			"rpcUrls": ["https://api.harmony.one"],
			"blockExplorerUrls": ["https://explorer.harmony.one/#/"]
		},
		"coingecko": "harmony"
	},
	{
		"alias": "harmony-testnet",
		"name": "Harmony Testnet",
		"logo": "https://cryptologos.cc/logos/harmony-one-logo.svg",
		"address": "0x7aF24c3fDb74e75C3c7751629C0C72785FDf3DAA",
		"chain": {
			"chainId": "0x6357d2e0",
			"chainName": "Harmony Testnet",
			"nativeCurrency": {
				"name": "ONE",
				"symbol": "ONE",
				"decimals": 18
			},
			"rpcUrls": ["https://api.s0.b.hmny.io"],
			"blockExplorerUrls": ["https://explorer.testnet.harmony.one/#/"]
		},
		"coingecko": "harmony"
	},
	{
		"alias": "bsc-testnet",
		"name": "BSC Testnet",
		"logo": "https://cryptologos.cc/logos/binance-coin-bnb-logo.svg",
		"address": "0x4b63C905089D6590eb996615d67D1A397731FC8C",
		"chain": {
			"chainId": "0x61",
			"chainName": "Binance Smart Chain Testnet",
			"nativeCurrency": {
				"name": "BNB",
				"symbol": "BNB",
				"decimals": 18
			},
			"rpcUrls": ["https://data-seed-prebsc-1-s1.binance.org:8545/"],
			"blockExplorerUrls": ["https://testnet.bscscan.com"]
		},
		"coingecko": "binancecoin"
	},
	{
		"name": "Matic Mumbai Testnet",
		"address": "0x2942513a1E63061d8EB868fb255E5594127f776f",
		"logo": "https://cryptologos.cc/logos/polygon-matic-logo.svg",
		"chainId": "0x13881",
		"unit": "MATIC",
		"coingecko": "matic-network"
	}
]
